airphin/__init__.py
airphin/constants.py
airphin/runner.py
airphin/cli/__init__.py
airphin/cli/command.py
airphin/core/__init__.py
airphin/core/rules/__init__.py
airphin/core/rules/config.py
airphin/core/rules/loader.py
airphin/core/transformer/__init__.py
airphin/core/transformer/imports.py
airphin/core/transformer/operators.py
airphin/core/transformer/route.py
airphin/fake/__init__.py
airphin/fake/core/__init__.py
airphin/fake/core/connection.py
airphin/fake/core/hook.py
airphin/fake/hooks/__init__.py
airphin/fake/hooks/mysql.py
airphin/fake/hooks/postgres.py
airphin/rules/core/dagContext.yaml
airphin/rules/hooks/MySqlHook.yaml
airphin/rules/hooks/PostgresHook.yaml
airphin/rules/operators/BashOperator.yaml
airphin/rules/operators/DummyOperator.yaml
airphin/rules/operators/PythonOperator.yaml
airphin/rules/operators/SparkSqlOperator.yaml
airphin/utils/__init__.py
airphin/utils/file.py
airphin/utils/string.py
airphin-0.0.13.dist-info/METADATA
airphin-0.0.13.dist-info/WHEEL
airphin-0.0.13.dist-info/entry_points.txt
airphin-0.0.13.dist-info/top_level.txt
airphin-0.0.13.dist-info/zip-safe
airphin-0.0.13.dist-info/RECORD
